dotslash/__init__.py
dotslash/__main__.py
dotslash/_locate.py
dotslash/py.typed
dotslash-0.5.8.data/scripts/dotslash
dotslash-0.5.8.dist-info/METADATA
dotslash-0.5.8.dist-info/WHEEL
dotslash-0.5.8.dist-info/RECORD
