Metadata-Version: 2.4
Name: dotslash
Version: 0.5.8
Summary: Command-line tool to facilitate fetching an executable, caching it, and then running it.
Project-URL: Homepage, https://dotslash-cli.com
Project-URL: Tracker, https://github.com/facebook/dotslash/issues
Project-URL: Source, https://github.com/facebook/dotslash
Author-email: Ofek Lev <oss@ofek.dev>
License-Expression: MIT OR Apache-2.0
Keywords: dotslash
Classifier: Development Status :: 5 - Production/Stable
Classifier: Intended Audience :: Developers
Classifier: Natural Language :: English
Classifier: Operating System :: OS Independent
Classifier: Programming Language :: Python :: Implementation :: CPython
Classifier: Programming Language :: Python :: Implementation :: PyPy
Requires-Python: >=3.10
